<?xml version="1.0" encoding="UTF-8"?>
<root>
    <item name="javax.swing.table.AbstractTableModel T[] getListeners(java.lang.Class&lt;T&gt;)">
        <annotation name="org.jetbrains.annotations.NotNull"/>
    </item>
    <item name="javax.swing.table.AbstractTableModel T[] getListeners(java.lang.Class&lt;T&gt;) 0">
        <annotation name="org.jetbrains.annotations.NotNull"/>
    </item>
    <item name="javax.swing.table.AbstractTableModel java.lang.Class&lt;?&gt; getColumnClass(int)">
        <annotation name="org.jetbrains.annotations.NotNull"/>
    </item>
    <item name="javax.swing.table.AbstractTableModel java.lang.String getColumnName(int)">
        <annotation name="org.jetbrains.annotations.NotNull"/>
    </item>
    <item name="javax.swing.table.AbstractTableModel javax.swing.event.TableModelListener[] getTableModelListeners()">
        <annotation name="org.jetbrains.annotations.NotNull"/>
    </item>
    <item name="javax.swing.table.DefaultTableCellRenderer java.awt.Component getTableCellRendererComponent(javax.swing.JTable, java.lang.Object, boolean, boolean, int, int)">
        <annotation name="org.jetbrains.annotations.NotNull"/>
    </item>
    <item name="javax.swing.table.DefaultTableCellRenderer java.awt.Component getTableCellRendererComponent(javax.swing.JTable, java.lang.Object, boolean, boolean, int, int) 0">
        <annotation name="org.jetbrains.annotations.NotNull"/>
    </item>
    <item name="javax.swing.table.DefaultTableCellRenderer void firePropertyChange(java.lang.String, java.lang.Object, java.lang.Object) 0">
        <annotation name="org.jetbrains.annotations.NotNull"/>
    </item>
    <item name="javax.swing.table.DefaultTableCellRenderer void repaint(java.awt.Rectangle) 0">
        <annotation name="org.jetbrains.annotations.NotNull"/>
    </item>
    <item name="javax.swing.table.DefaultTableCellRenderer void setValue(java.lang.Object) 0">
        <annotation name="org.jetbrains.annotations.NotNull"/>
    </item>
    <item name="javax.swing.table.DefaultTableColumnModel T[] getListeners(java.lang.Class&lt;T&gt;)">
        <annotation name="org.jetbrains.annotations.NotNull"/>
    </item>
    <item name="javax.swing.table.DefaultTableColumnModel T[] getListeners(java.lang.Class&lt;T&gt;) 0">
        <annotation name="org.jetbrains.annotations.NotNull"/>
    </item>
    <item name="javax.swing.table.DefaultTableColumnModel int getColumnIndex(java.lang.Object) 0">
        <annotation name="org.jetbrains.annotations.NotNull"/>
    </item>
    <item name="javax.swing.table.DefaultTableColumnModel int[] getSelectedColumns()">
        <annotation name="org.jetbrains.annotations.NotNull"/>
    </item>
    <item name="javax.swing.table.DefaultTableColumnModel java.util.Enumeration&lt;javax.swing.table.TableColumn&gt; getColumns()">
        <annotation name="org.jetbrains.annotations.NotNull"/>
    </item>
    <item name="javax.swing.table.DefaultTableColumnModel javax.swing.ListSelectionModel createSelectionModel()">
        <annotation name="org.jetbrains.annotations.NotNull"/>
    </item>
    <item name="javax.swing.table.DefaultTableColumnModel javax.swing.event.TableColumnModelListener[] getColumnModelListeners()">
        <annotation name="org.jetbrains.annotations.NotNull"/>
    </item>
    <item name="javax.swing.table.DefaultTableColumnModel void addColumn(javax.swing.table.TableColumn) 0">
        <annotation name="org.jetbrains.annotations.NotNull"/>
    </item>
    <item name="javax.swing.table.DefaultTableColumnModel void propertyChange(java.beans.PropertyChangeEvent) 0">
        <annotation name="org.jetbrains.annotations.NotNull"/>
    </item>
    <item name="javax.swing.table.DefaultTableColumnModel void setSelectionModel(javax.swing.ListSelectionModel) 0">
        <annotation name="org.jetbrains.annotations.NotNull"/>
    </item>
    <item name="javax.swing.table.DefaultTableColumnModel void valueChanged(javax.swing.event.ListSelectionEvent) 0">
        <annotation name="org.jetbrains.annotations.NotNull"/>
    </item>
    <item name="javax.swing.table.DefaultTableModel java.lang.String getColumnName(int)">
        <annotation name="org.jetbrains.annotations.NotNull"/>
    </item>
    <item name="javax.swing.table.DefaultTableModel void newRowsAdded(javax.swing.event.TableModelEvent) 0">
        <annotation name="org.jetbrains.annotations.NotNull"/>
    </item>
    <item name="javax.swing.table.JTableHeader int columnAtPoint(java.awt.Point) 0">
        <annotation name="org.jetbrains.annotations.NotNull"/>
    </item>
    <item name="javax.swing.table.JTableHeader java.awt.Rectangle getHeaderRect(int)">
        <annotation name="org.jetbrains.annotations.NotNull"/>
    </item>
    <item name="javax.swing.table.JTableHeader java.lang.String getToolTipText(java.awt.event.MouseEvent) 0">
        <annotation name="org.jetbrains.annotations.NotNull"/>
    </item>
    <item name="javax.swing.table.JTableHeader java.lang.String getUIClassID()">
        <annotation name="org.jetbrains.annotations.NotNull"/>
    </item>
    <item name="javax.swing.table.JTableHeader java.lang.String paramString()">
        <annotation name="org.jetbrains.annotations.NotNull"/>
    </item>
    <item name="javax.swing.table.JTableHeader javax.swing.table.TableCellRenderer createDefaultRenderer()">
        <annotation name="org.jetbrains.annotations.NotNull"/>
    </item>
    <item name="javax.swing.table.JTableHeader javax.swing.table.TableColumnModel createDefaultColumnModel()">
        <annotation name="org.jetbrains.annotations.NotNull"/>
    </item>
    <item name="javax.swing.table.JTableHeader void columnAdded(javax.swing.event.TableColumnModelEvent) 0">
        <annotation name="org.jetbrains.annotations.NotNull"/>
    </item>
    <item name="javax.swing.table.JTableHeader void columnMoved(javax.swing.event.TableColumnModelEvent) 0">
        <annotation name="org.jetbrains.annotations.NotNull"/>
    </item>
    <item name="javax.swing.table.JTableHeader void columnRemoved(javax.swing.event.TableColumnModelEvent) 0">
        <annotation name="org.jetbrains.annotations.NotNull"/>
    </item>
    <item name="javax.swing.table.JTableHeader void columnSelectionChanged(javax.swing.event.ListSelectionEvent) 0">
        <annotation name="org.jetbrains.annotations.NotNull"/>
    </item>
    <item name="javax.swing.table.JTableHeader void setColumnModel(javax.swing.table.TableColumnModel) 0">
        <annotation name="org.jetbrains.annotations.NotNull"/>
    </item>
    <item name="javax.swing.table.JTableHeader.AccessibleJTableHeader javax.accessibility.Accessible getAccessibleAt(java.awt.Point) 0">
        <annotation name="org.jetbrains.annotations.NotNull"/>
    </item>
    <item name="javax.swing.table.JTableHeader.AccessibleJTableHeader javax.accessibility.AccessibleRole getAccessibleRole()">
        <annotation name="org.jetbrains.annotations.NotNull"/>
    </item>
    <item name="javax.swing.table.JTableHeader.AccessibleJTableHeader.AccessibleJTableHeaderEntry boolean contains(java.awt.Point) 0">
        <annotation name="org.jetbrains.annotations.NotNull"/>
    </item>
    <item name="javax.swing.table.JTableHeader.AccessibleJTableHeader.AccessibleJTableHeaderEntry java.awt.Dimension getSize()">
        <annotation name="org.jetbrains.annotations.NotNull"/>
    </item>
    <item name="javax.swing.table.JTableHeader.AccessibleJTableHeader.AccessibleJTableHeaderEntry java.awt.Point getLocation()">
        <annotation name="org.jetbrains.annotations.NotNull"/>
    </item>
    <item name="javax.swing.table.JTableHeader.AccessibleJTableHeader.AccessibleJTableHeaderEntry java.awt.Rectangle getBounds()">
        <annotation name="org.jetbrains.annotations.NotNull"/>
    </item>
    <item name="javax.swing.table.JTableHeader.AccessibleJTableHeader.AccessibleJTableHeaderEntry javax.accessibility.Accessible getAccessibleAt(java.awt.Point) 0">
        <annotation name="org.jetbrains.annotations.NotNull"/>
    </item>
    <item name="javax.swing.table.JTableHeader.AccessibleJTableHeader.AccessibleJTableHeaderEntry javax.accessibility.AccessibleComponent getAccessibleComponent()">
        <annotation name="org.jetbrains.annotations.NotNull"/>
    </item>
    <item name="javax.swing.table.JTableHeader.AccessibleJTableHeader.AccessibleJTableHeaderEntry javax.accessibility.AccessibleContext getAccessibleContext()">
        <annotation name="org.jetbrains.annotations.NotNull"/>
    </item>
    <item name="javax.swing.table.JTableHeader.AccessibleJTableHeader.AccessibleJTableHeaderEntry void setBounds(java.awt.Rectangle) 0">
        <annotation name="org.jetbrains.annotations.NotNull"/>
    </item>
    <item name="javax.swing.table.JTableHeader.AccessibleJTableHeader.AccessibleJTableHeaderEntry void setLocation(java.awt.Point) 0">
        <annotation name="org.jetbrains.annotations.NotNull"/>
    </item>
    <item name="javax.swing.table.JTableHeader.AccessibleJTableHeader.AccessibleJTableHeaderEntry void setSize(java.awt.Dimension) 0">
        <annotation name="org.jetbrains.annotations.NotNull"/>
    </item>
    <item name="javax.swing.table.TableCellRenderer java.awt.Component getTableCellRendererComponent(javax.swing.JTable, java.lang.Object, boolean, boolean, int, int)">
        <annotation name="org.jetbrains.annotations.NotNull"/>
    </item>
    <item name="javax.swing.table.TableCellRenderer java.awt.Component getTableCellRendererComponent(javax.swing.JTable, java.lang.Object, boolean, boolean, int, int) 0">
        <annotation name="org.jetbrains.annotations.NotNull"/>
    </item>
    <item name="javax.swing.table.TableColumn javax.swing.table.TableCellRenderer createDefaultHeaderRenderer()">
        <annotation name="org.jetbrains.annotations.NotNull"/>
    </item>
    <item name="javax.swing.table.TableColumnModel int getColumnIndex(java.lang.Object) 0">
        <annotation name="org.jetbrains.annotations.NotNull"/>
    </item>
    <item name="javax.swing.table.TableColumnModel int[] getSelectedColumns()">
        <annotation name="org.jetbrains.annotations.NotNull"/>
    </item>
    <item name="javax.swing.table.TableColumnModel java.util.Enumeration&lt;javax.swing.table.TableColumn&gt; getColumns()">
        <annotation name="org.jetbrains.annotations.NotNull"/>
    </item>
    <item name="javax.swing.table.TableColumnModel void addColumn(javax.swing.table.TableColumn) 0">
        <annotation name="org.jetbrains.annotations.NotNull"/>
    </item>
    <item name="javax.swing.table.TableColumnModel void setSelectionModel(javax.swing.ListSelectionModel) 0">
        <annotation name="org.jetbrains.annotations.NotNull"/>
    </item>
    <item name="javax.swing.table.TableModel java.lang.Class&lt;?&gt; getColumnClass(int)">
        <annotation name="org.jetbrains.annotations.NotNull"/>
    </item>
    <item name="javax.swing.table.TableModel java.lang.String getColumnName(int)">
        <annotation name="org.jetbrains.annotations.NotNull"/>
    </item>
</root>

