{
  "frozen": {
    "default": 0,
    "false": 0,
    "true": 1
  },
  "liftShorter": {
    "default": 0,
    "false": 0,
    "true": 1
  },
  "liftShorterClasses": {
    "default": 0,
    "false": 0,
    "true": 1
  },
  "middleMatching": {
    "default": 0,
    "false": 0,
    "true": 1
  },
  "nonGeneric": {
    "0": 0,
    "1": 1,
    "default": 0
  },
  "prox_inResolveScope": {
    "default": 1,
    "false": 0,
    "true": 1
  },
  "prox_openedInEditor": {
    "default": 0,
    "false": 0,
    "true": 1
  },
  "prox_rubyOwnCode": {
    "1": 1,
    "default": 0,
    "null": 0
  },
  "prox_sameDirectory": {
    "default": 0,
    "false": 0,
    "true": 1
  },
  "prox_sameLogicalRoot": {
    "default": 0,
    "false": 0,
    "true": 1
  },
  "prox_sdkOrLibrary": {
    "default": 0,
    "false": 0,
    "true": 1
  },
  "simple": {
    "0": 0,
    "10": 1,
    "default": 0
  },
  "sorter": {
    "1": 1,
    "2": 0,
    "default": 1
  },
  "templates": {
    "default": 0,
    "false": 0,
    "true": 1
  }
}